gbscli/__init__.py
gbscli/entrypoint.py
tests/__init__.py
tests/test_gbscli.py
gbscli-0.1.0.dist-info/LICENSE
gbscli-0.1.0.dist-info/METADATA
gbscli-0.1.0.dist-info/WHEEL
gbscli-0.1.0.dist-info/entry_points.txt
gbscli-0.1.0.dist-info/top_level.txt
gbscli-0.1.0.dist-info/RECORD
