Metadata-Version: 2.1
Name: gbscli
Version: 0.1.0
Summary: GreedyBandit CLI
Home-page: https://github.com/boxnwhiskr/gbscli
Author: Box and Whisker
Author-email: box@boxnwhis.kr
License: UNKNOWN
Platform: UNKNOWN
Classifier: Environment :: Console
Classifier: Intended Audience :: Developers
Classifier: Intended Audience :: Information Technology
Classifier: Intended Audience :: Science/Research
Classifier: Intended Audience :: System Administrators
Classifier: License :: OSI Approved :: MIT License
Classifier: Natural Language :: English
Classifier: Programming Language :: Python :: 3
Classifier: Programming Language :: Python :: 3.4
Classifier: Programming Language :: Python :: 3.5
Classifier: Programming Language :: Python :: 3.6
Classifier: Programming Language :: Python :: 3.7
Classifier: Operating System :: OS Independent
Requires-Dist: click (==7.0)
Requires-Dist: requests (==2.21.0)
